LICENSE
README.md
SECURITY.md
SETUP.py
requirements.txt
setup.cfg
setup.py
test_example.py
test_monthly_data.png
test_scaled_daily_data.png
.github/ISSUE_TEMPLATE/bug_report.md
.github/ISSUE_TEMPLATE/custom.md
.github/ISSUE_TEMPLATE/feature_request.md
aioTrends/HandleExceptions.py
aioTrends/Settings.py
aioTrends/Trends.py
aioTrends/__init__.py
aioTrends/processData.py
aioTrends.egg-info/PKG-INFO
aioTrends.egg-info/SOURCES.txt
aioTrends.egg-info/dependency_links.txt
aioTrends.egg-info/requires.txt
aioTrends.egg-info/top_level.txt
data/IOT
data/qrys.pkl
proxies/proxies.txt
settings/settings.json
settings/userAgents.json