Metadata-Version: 2.1
Name: aioTrends
Version: 0.0.4
Summary: Library for fetching Google Trends in an async. way
Home-page: https://github.com/yuz0101/aioTrends
Download-URL: https://github.com/yuz0101/aioTrends/archive/refs/tags/v_04.tar.gz
Author: Stephen Zhang
Author-email: stephen_se@outlook.com
License: MIT
Keywords: google,trends,async,asyncio,aiohttp,googletrends,pytrends
Classifier: Intended Audience :: Developers
Classifier: License :: OSI Approved :: MIT License
Classifier: Programming Language :: Python :: 3.10
Classifier: Programming Language :: Python :: 3.11
Classifier: Operating System :: OS Independent
License-File: LICENSE
